{
  "main": {
    "name":"Sanat Nayar",
    "occupation":"(Your Occupation Here)",
    "description":"Here will be your description. Use this to describe what you do or whatever you feel best describes yourself to a potential employer",
    "image":"profilepic.jpg",
    "bio":"Use this bio section as your way of describing yourself and saying what you do, what technologies you like to use or feel most comfortable with, describing your personality, or whatever else you feel like throwing in.",
    "contactmessage":"Here is where you should write your message to readers to have them get in contact with you.",
    "email": "youremailhere@gmail.com",
    "phone": "555-555-5555",
    "address":{
      "street":"(Your Street)",
      "city":"(Your City)",
      "state":"(Your State)",
      "zip": "(Your Zip/Postal Code)"
    },
    "website": "http://www.timbakerdev.com",
    "resumedownload":"http://timbakerdev.com",
    "social":[
      {
        "name":"facebook",
        "url":"http://facebook.com/tim.baker.906",
        "className":"fa fa-facebook"
      },
      {
        "name":"twitter",
        "url":"http://twitter.com",
        "className":"fa fa-twitter"
      },
      {
        "name":"google-plus",
        "url":"http://googleplus.com/tbakerx",
        "className":"fa fa-google-plus"
      },
      {
        "name":"linkedin",
        "url":"https://www.linkedin.com/in/tim-baker-8420009a/",
        "className":"fa fa-linkedin"
      },
      {
        "name":"instagram",
        "url":"http://instagram.com/tbaker_x",
        "className":"fa fa-instagram"
      },
      {
        "name":"github",
        "url":"http://github.com/tbakerx",
        "className":"fa fa-github"
      },
      {
        "name":"skype",
        "url":"http://skype.com",
        "className":"fa fa-skype"
      }
    ]
  },
  "resume":{
    "skillmessage":"Here you can create a short write-up of your skills to show off to employers",
    "education":[
      {
        "school":"University of Ottawa",
        "degree":"BASc in Computer Engineering and Entrepreneurship",
        "graduated":"Graduating December 2021",
        "description":"3.85/4.00 CGPA"
      },
      {
        "school":"Earl of March Secondary School",
        "degree":"High School Diploma",
        "graduated":"June 2017",
        "description":"91% Average"
      }
    ],
    "work":[
      {
        "company":"Canadian Border Services Agency (CBSA)",
        "title":"IT Student",
        "years":"March 2010 - Present",
        "description":"Describe work, special projects, notable achievements, what technologies you have been working with, and anything else that would be useful for an employer to know."
      },
      {
        "company":"Super Cool Studio",
        "title":"Junior bug fixer",
        "years":"March 2007 - February 2010",
        "description":"Describe work, special projects, notable achievements, what technologies you have been working with, and anything else that would be useful for an employer to know."
      }
    ],
    "skills":[
      {
        "name":"Java",
        "level":"70%"
      },
      {
        "name":"Python (including NumPy and OpenCV)",
        "level":"70%"
      },
      {
        "name":"HTML/CSS/JS",
        "level":"50%"
      },
      {
        "name":"MySQL/PHP",
        "level":"60%"
      },
      {
        "name":"Visual Basics",
        "level":"65%"
      },
      {
        "name":"C",
        "level":"50%"
      },
      {
        "name":"Git VS",
        "level":"80%"
      }

    ]
  },
  "portfolio":{
    "projects": [
      {
        "title":"Minesweeper",
        "category":"Minesweeper Application Using MVC Architectural Pattern",
        "image":"free-minesweeper-thumbnail.png",
        "url":"https://www.canadianwanderlust.com"
      },
      {
        "title":"Fury Fighting Gear",
        "category":"(offline now) A fighting gear company I started",
        "image":"fury-fighting-gear.jpg",
        "url":"http://www.timbakerdev.com"
      },
      {
        "title":"Original Thai Food",
        "category":"Website I built for a restaurant I like in Thailand",
        "image":"original-thai-food.jpg",
        "url":"http://www.timbakerdev.com/originalthaifood.github.io"
      },
      {
        "title":"Resume Website",
        "category":"A React based resume website template",
        "image":"resume-website.jpg",
        "url":"http://www.timbakerdev.com"
      },
      {
        "title":"Smirkspace",
        "category":"(MVP Only) A React and Meteor based chat University project.",
        "image":"smirkspace.jpg",
        "url":"http://www.smirkspace.com"
      }
    ]
  }
}
